llm_static_assert/__init__.py
llm_static_assert/llm_static_assert.py
llm_static_assert/llm_static_assert_options.py
llm_static_assert/prompts.py
llm_static_assert-0.1.0.dist-info/LICENSE
llm_static_assert-0.1.0.dist-info/METADATA
llm_static_assert-0.1.0.dist-info/WHEEL
llm_static_assert-0.1.0.dist-info/RECORD
