Metadata-Version: 2.1
Name: llm-static-assert
Version: 0.1.0
Summary: A Python library that leverages Language Models (LLMs) to perform static assertions on code, combining natural language flexibility with static analysis rigor.
Home-page: https://github.com/kdunee/llm-static-assert
License: MIT
Keywords: llm,static-analysis,assertions,code-quality,natural-language
Author: Kosma Dunikowski
Author-email: kosmadunikowski@gmail.com
Requires-Python: >=3.10,<4.0
Classifier: Intended Audience :: Developers
Classifier: License :: OSI Approved :: MIT License
Classifier: Programming Language :: Python :: 3
Classifier: Programming Language :: Python :: 3.10
Classifier: Programming Language :: Python :: 3.11
Classifier: Programming Language :: Python :: 3.12
Classifier: Programming Language :: Python :: 3.13
Classifier: Topic :: Software Development :: Quality Assurance
Classifier: Topic :: Software Development :: Testing
Requires-Dist: litellm (>=1.49.2,<2.0.0)
